<annotation>
	<folder>Pepper corns</folder>
	<filename>20210426_190938.jpg</filename>
	<path>C:\Users\ademo\Downloads\Recipes\Kadhi Pakora\Pepper corns\20210426_190938.jpg</path>
	<source>
		<database>Unknown</database>
	</source>
	<size>
		<width>4032</width>
		<height>3024</height>
		<depth>3</depth>
	</size>
	<segmented>0</segmented>
	<object>
		<name>pepper corns</name>
		<pose>Unspecified</pose>
		<truncated>0</truncated>
		<difficult>0</difficult>
		<bndbox>
			<xmin>928</xmin>
			<ymin>578</ymin>
			<xmax>2999</xmax>
			<ymax>1664</ymax>
		</bndbox>
	</object>
</annotation>
