<annotation>
	<folder>Pinto Beans (kidney beans)</folder>
	<filename>20210606_172843.jpg</filename>
	<path>/Users/rey/Desktop/Doc/Study Mat./Docs/M.sc/Sem3rd/Cooking Recipe/Coverted Data/INGREDIENTS/add/Pinto Beans (kidney beans)/20210606_172843.jpg</path>
	<source>
		<database>Unknown</database>
	</source>
	<size>
		<width>256</width>
		<height>256</height>
		<depth>3</depth>
	</size>
	<segmented>0</segmented>
	<object>
		<name>Pinto Beans (kidney beans)</name>
		<pose>Unspecified</pose>
		<truncated>0</truncated>
		<difficult>0</difficult>
		<bndbox>
			<xmin>38</xmin>
			<ymin>43</ymin>
			<xmax>244</xmax>
			<ymax>215</ymax>
		</bndbox>
	</object>
	<object>
		<name>Pinto Beans (kidney beans)</name>
		<pose>Unspecified</pose>
		<truncated>0</truncated>
		<difficult>0</difficult>
		<bndbox>
			<xmin>47</xmin>
			<ymin>117</ymin>
			<xmax>96</xmax>
			<ymax>163</ymax>
		</bndbox>
	</object>
	<object>
		<name>Pinto Beans (kidney beans)</name>
		<pose>Unspecified</pose>
		<truncated>0</truncated>
		<difficult>0</difficult>
		<bndbox>
			<xmin>79</xmin>
			<ymin>65</ymin>
			<xmax>128</xmax>
			<ymax>126</ymax>
		</bndbox>
	</object>
	<object>
		<name>Pinto Beans (kidney beans)</name>
		<pose>Unspecified</pose>
		<truncated>0</truncated>
		<difficult>0</difficult>
		<bndbox>
			<xmin>125</xmin>
			<ymin>51</ymin>
			<xmax>170</xmax>
			<ymax>101</ymax>
		</bndbox>
	</object>
	<object>
		<name>Pinto Beans (kidney beans)</name>
		<pose>Unspecified</pose>
		<truncated>0</truncated>
		<difficult>0</difficult>
		<bndbox>
			<xmin>177</xmin>
			<ymin>65</ymin>
			<xmax>207</xmax>
			<ymax>125</ymax>
		</bndbox>
	</object>
	<object>
		<name>Pinto Beans (kidney beans)</name>
		<pose>Unspecified</pose>
		<truncated>0</truncated>
		<difficult>0</difficult>
		<bndbox>
			<xmin>196</xmin>
			<ymin>89</ymin>
			<xmax>246</xmax>
			<ymax>151</ymax>
		</bndbox>
	</object>
	<object>
		<name>Pinto Beans (kidney beans)</name>
		<pose>Unspecified</pose>
		<truncated>0</truncated>
		<difficult>0</difficult>
		<bndbox>
			<xmin>134</xmin>
			<ymin>110</ymin>
			<xmax>178</xmax>
			<ymax>188</ymax>
		</bndbox>
	</object>
	<object>
		<name>Pinto Beans (kidney beans)</name>
		<pose>Unspecified</pose>
		<truncated>0</truncated>
		<difficult>0</difficult>
		<bndbox>
			<xmin>83</xmin>
			<ymin>133</ymin>
			<xmax>144</xmax>
			<ymax>203</ymax>
		</bndbox>
	</object>
	<object>
		<name>Pinto Beans (kidney beans)</name>
		<pose>Unspecified</pose>
		<truncated>0</truncated>
		<difficult>0</difficult>
		<bndbox>
			<xmin>124</xmin>
			<ymin>162</ymin>
			<xmax>194</xmax>
			<ymax>199</ymax>
		</bndbox>
	</object>
</annotation>
